pywebgo/__init__.py
pywebgo/controller.py
pywebgo/data.py
pywebgo/elements.py
pywebgo/utils.py
pywebgo-0.0.12.dist-info/METADATA
pywebgo-0.0.12.dist-info/WHEEL
pywebgo-0.0.12.dist-info/licenses/LICENSE
pywebgo-0.0.12.dist-info/RECORD
