Metadata-Version: 2.1
Name: pywebgo
Version: 0.0.12
Summary: A selenium client that automates web surfing with simple commands.
Project-URL: Homepage, https://github.com/adilzafar66/pywebgo
Project-URL: Bug Tracker, https://github.com/adilzafar66/pywebgo/issues
Author-email: Adil Zafar Khan <adilzafar66@gmail.com>
License-File: LICENSE
Classifier: License :: OSI Approved :: MIT License
Classifier: Operating System :: OS Independent
Classifier: Programming Language :: Python :: 3
Requires-Python: >=3.7
